design.sv
module structuralProject(F1, F2, F3, a, b, c, d);
  input a, b, c, d;
  output F1, F2, F3;
  
  wire inva, invb, invc, invd;
  
  not (inva, a);
  not (invb, b);
  not (invc, c);
  not (invd, d);
  
  setF1 fistBit(F1, a, b, c, d);
  setF2 secondBit(F2, a, b, c, d);
  setF3 thirdBit(F3, a, b, c, d);
  
endmodule

module setF1(F1, a, b, c, d);
  // bc' + a'bd' + ab'cd
  input a, b, c, d;
  output F1;
  
  wire term1, term2, term3;
  
  and and1 (term1, b, structuralProject.invc);
  and and2 (term2, structuralProject.inva, b, structuralProject.invd);
  and and3 (term3, a, structuralProject.invb, c, d);
  
  or or1 (F1, term1, term2, term3);
endmodule

module setF2(F2, a, b, c, d);
  // a'b'c (term1) + a'cd'(term2) + ac'd (term3) + b'cd' (term4)
  input a, b, c, d;
  output F2;
  
  wire term1, term2, term3, term4;

  and and1 (term1, structuralProject.inva, structuralProject.invb, c);
  and and2 (term2, structuralProject.inva, c, structuralProject.invd);
  and and3 (term3, a, structuralProject.invc, d);
  and and4 (term4, structuralProject.invb, c, structuralProject.invd);
  
  or or1 (F2, term1, term2, term3, term4);
endmodule


module setF3(F3, a, b, c, d);
  // a'b'd (term1) + a'c'd(term2) + ab'd'(term3) + ac'd'(term4) + abcd(term5)
  input a, b, c, d;
  output F3;
  
  wire term1, term2, term3, term4, term5;
 
  
  and and1 (term1, structuralProject.inva, structuralProject.invb, d);
  and and2 (term2, structuralProject.inva, structuralProject.invc, d);
  and and3 (term3, a, structuralProject.invb, structuralProject.invd);
  and and4 (term4, a, structuralProject.invc, structuralProject.invd);
  and and5 (term5, a, b, c, d);
  
  or or1 (F3 ,term1, term2, term3, term4, term5);
endmodule

testbench.sv
module testbench();
  reg a, b, c, d;
  wire F1, F2, F3;
  structuralProject teste(F1, F2, F3, a, b, c, d);

  initial begin
    $dumpfile("dump.vcd");
    $dumpvars(0, testbench);

    $display("A | B | C | D | Result");
    $display("--|---|---|---|-------");


    // Test minterm 0
    a = 0; b = 0; c = 0; d = 0; $display("%b | %b | %b | %b | %b %b %b", a, b, c, d, F1, F2, F3);#5;

    // Test minterm 1
    a = 0; b = 0; c = 0; d = 1; $display("%b | %b | %b | %b | %b %b %b", a, b, c, d, F1, F2, F3); #5; 

    // Test minterms 2 to 7
    a = 0; b = 0; c = 1; d = 0; $display("%b | %b | %b | %b | %b %b %b", a, b, c, d, F1, F2, F3); #5;
    a = 0; b = 0; c = 1; d = 1; $display("%b | %b | %b | %b | %b %b %b", a, b, c, d, F1, F2, F3); #5;
    a = 0; b = 1; c = 0; d = 0; $display("%b | %b | %b | %b | %b %b %b", a, b, c, d, F1, F2, F3); #5;
    a = 0; b = 1; c = 0; d = 1; $display("%b | %b | %b | %b | %b %b %b", a, b, c, d, F1, F2, F3); #5;
    a = 0; b = 1; c = 1; d = 0; $display("%b | %b | %b | %b | %b %b %b", a, b, c, d, F1, F2, F3); #5;
    a = 0; b = 1; c = 1; d = 1; $display("%b | %b | %b | %b | %b %b %b", a, b, c, d, F1, F2, F3); #5;

    // Test minterms 8 to 15
    a = 1; b = 0; c = 0; d = 0; $display("%b | %b | %b | %b | %b %b %b", a, b, c, d, F1, F2, F3); #5;
    a = 1; b = 0; c = 0; d = 1; $display("%b | %b | %b | %b | %b %b %b", a, b, c, d, F1, F2, F3); #5;
    a = 1; b = 0; c = 1; d = 0; $display("%b | %b | %b | %b | %b %b %b", a, b, c, d, F1, F2, F3); #5;
    a = 1; b = 0; c = 1; d = 1; $display("%b | %b | %b | %b | %b %b %b", a, b, c, d, F1, F2, F3); #5;
    a = 1; b = 1; c = 0; d = 0; $display("%b | %b | %b | %b | %b %b %b", a, b, c, d, F1, F2, F3); #5;
    a = 1; b = 1; c = 0; d = 1; $display("%b | %b | %b | %b | %b %b %b", a, b, c, d, F1, F2, F3); #5;
    a = 1; b = 1; c = 1; d = 0; $display("%b | %b | %b | %b | %b %b %b", a, b, c, d, F1, F2, F3); #5;
    a = 1; b = 1; c = 1; d = 1; $display("%b | %b | %b | %b | %b %b %b", a, b, c, d, F1, F2, F3); #5;

    $finish;
  end
endmodule

dump.vcd
$date
	Mon Nov  6 17:12:19 2023
$end
$version
	Icarus Verilog
$end
$timescale
	1s
$end
$scope module testbench $end
$var wire 1 ! F3 $end
$var wire 1 " F2 $end
$var wire 1 # F1 $end
$var reg 1 $ a $end
$var reg 1 % b $end
$var reg 1 & c $end
$var reg 1 ' d $end
$scope module teste $end
$var wire 1 $ a $end
$var wire 1 % b $end
$var wire 1 & c $end
$var wire 1 ' d $end
$var wire 1 ( inva $end
$var wire 1 ) invb $end
$var wire 1 * invc $end
$var wire 1 + invd $end
$var wire 1 ! F3 $end
$var wire 1 " F2 $end
$var wire 1 # F1 $end
$scope module fistBit $end
$var wire 1 # F1 $end
$var wire 1 $ a $end
$var wire 1 % b $end
$var wire 1 & c $end
$var wire 1 ' d $end
$var wire 1 , term1 $end
$var wire 1 - term2 $end
$var wire 1 . term3 $end
$upscope $end
$scope module secondBit $end
$var wire 1 " F2 $end
$var wire 1 $ a $end
$var wire 1 % b $end
$var wire 1 & c $end
$var wire 1 ' d $end
$var wire 1 / term1 $end
$var wire 1 0 term2 $end
$var wire 1 1 term3 $end
$var wire 1 2 term4 $end
$upscope $end
$scope module thirdBit $end
$var wire 1 ! F3 $end
$var wire 1 $ a $end
$var wire 1 % b $end
$var wire 1 & c $end
$var wire 1 ' d $end
$var wire 1 3 term1 $end
$var wire 1 4 term2 $end
$var wire 1 5 term3 $end
$var wire 1 6 term4 $end
$var wire 1 7 term5 $end
$upscope $end
$upscope $end
$upscope $end
$enddefinitions $end
#0
$dumpvars
07
06
05
04
03
02
01
00
0/
0.
0-
0,
1+
1*
1)
1(
0'
0&
0%
0$
0#
0"
0!
$end
#5
1!
0+
13
14
1'
#10
0!
10
12
1"
1+
03
04
0*
1/
0'
1&
#15
1!
00
02
0+
13
1'
#20
0!
1#
1-
1,
0"
1+
03
1*
0/
0)
0'
0&
1%
#25
1!
0-
0+
14
1'
#30
1"
0!
1-
10
0,
1+
04
0*
0'
1&
#35
0#
0"
0-
00
0+
1'
#40
1!
16
15
1+
1*
1)
0(
0'
0&
0%
1$
#45
0!
05
06
1"
0+
11
1'
#50
1!
12
15
1"
1+
01
0*
0'
1&
#55
0!
0"
02
05
1#
0+
1.
1'
#60
1!
1,
16
1#
1+
1*
0.
0)
0'
0&
1%
#65
0!
06
1"
0+
11
1'
#70
0#
0"
0,
1+
01
0*
0'
1&
#75
1!
0+
17
1'
